publicholiday/__init__.py
publicholiday/cli.py
publicholiday-0.1.8.dist-info/METADATA
publicholiday-0.1.8.dist-info/RECORD
publicholiday-0.1.8.dist-info/WHEEL
publicholiday-0.1.8.dist-info/entry_points.txt
publicholiday-0.1.8.dist-info/top_level.txt
